LaminB_Phenotyping.py
LaminB_ID-3.0.0.dist-info/LICENSE
LaminB_ID-3.0.0.dist-info/METADATA
LaminB_ID-3.0.0.dist-info/WHEEL
LaminB_ID-3.0.0.dist-info/entry_points.txt
LaminB_ID-3.0.0.dist-info/top_level.txt
LaminB_ID-3.0.0.dist-info/RECORD
