Metadata-Version: 2.1
Name: LaminB-ID
Version: 3.0.0
Summary: This project improves the current method of phenotyping Lamin B staining.
Author-email: "Todd E. Stang" <todds360@gmail.com>
Maintainer-email: Todd Stang <todds360@gmail.com>
Project-URL: Homepage, https://github.com/tes465/LaminB-ID
Project-URL: Bug Reports, https://github.com/tes465/LaminB-ID/issues
Project-URL: Source, https://github.com/tes465/LaminB-ID/
Keywords: LaminB,Nuclear Pore Complex,Nuclear Pore Complex
Classifier: Development Status :: 3 - Alpha
Classifier: Intended Audience :: Science/Research
Classifier: License :: OSI Approved :: GNU General Public License v3 (GPLv3)
Classifier: Programming Language :: Python :: 3
Classifier: Programming Language :: Python :: 3.7
Classifier: Programming Language :: Python :: 3.8
Classifier: Programming Language :: Python :: 3.9
Classifier: Programming Language :: Python :: 3.10
Classifier: Programming Language :: Python :: 3.11
Classifier: Programming Language :: Python :: 3 :: Only
Requires-Python: >=3.0
License-File: LICENSE
